billionprompt/HTTPClient.py
billionprompt/ImageClient.py
billionprompt/PromptClient.py
billionprompt/RetrivalClient.py
billionprompt/__init__.py
billionprompt/utils.py
billionprompt-0.0.2.dist-info/LICENSE
billionprompt-0.0.2.dist-info/METADATA
billionprompt-0.0.2.dist-info/WHEEL
billionprompt-0.0.2.dist-info/top_level.txt
billionprompt-0.0.2.dist-info/RECORD
