Metadata-Version: 2.1
Name: billionprompt
Version: 0.0.2
Summary: BillionPrompt Python SDK
Home-page: 
Author: ShanHai AI
Author-email: xiexiaofeng@youxiqun.com
Classifier: Programming Language :: Python :: 3
Classifier: License :: OSI Approved :: Apache Software License
Classifier: Operating System :: OS Independent
License-File: LICENSE
Requires-Dist: requests
